datastructures/__init__.py
datastructures/graphalgo/__init__.py
datastructures/graphalgo/graph.py
datastructures/heap/__init__.py
datastructures/heap/vector_heap.py
datastructures/linear/CDLL.py
datastructures/linear/CSLL.py
datastructures/linear/DLL.py
datastructures/linear/QueueLL.py
datastructures/linear/SLL.py
datastructures/linear/StackLL.py
datastructures/linear/__init__.py
datastructures/nodes/DNode.py
datastructures/nodes/SNode.py
datastructures/nodes/TNode.py
datastructures/nodes/__init__.py
datastructures/trees/AVL.py
datastructures/trees/BST.py
datastructures/trees/__init__.py
libds-0.3.dist-info/METADATA
libds-0.3.dist-info/WHEEL
libds-0.3.dist-info/top_level.txt
libds-0.3.dist-info/RECORD
